CHANGES.txt
LICENSE.txt
MANIFEST.in
README.txt
bootstrap.py
buildout.cfg
setup.py
src/j01/__init__.py
src/j01.dialog.egg-info/PKG-INFO
src/j01.dialog.egg-info/SOURCES.txt
src/j01.dialog.egg-info/dependency_links.txt
src/j01.dialog.egg-info/namespace_packages.txt
src/j01.dialog.egg-info/not-zip-safe
src/j01.dialog.egg-info/requires.txt
src/j01.dialog.egg-info/top_level.txt
src/j01/dialog/README.txt
src/j01/dialog/README_MIGRATION_P2P3.py
src/j01/dialog/__init__.py
src/j01/dialog/browser.zcml
src/j01/dialog/btn.py
src/j01/dialog/checker.txt
src/j01/dialog/checker_MIGRATION_P2P3.py
src/j01/dialog/configure.zcml
src/j01/dialog/dialog.pt
src/j01/dialog/iframe.pt
src/j01/dialog/iframe_redirect.pt
src/j01/dialog/iframe_reload.pt
src/j01/dialog/iframe_reload_content.pt
src/j01/dialog/interfaces.py
src/j01/dialog/jsform.py
src/j01/dialog/jsonrpc.py
src/j01/dialog/jsonrpc.zcml
src/j01/dialog/jspage.py
src/j01/dialog/layout_iframe.pt
src/j01/dialog/link.py
src/j01/dialog/tests.py
src/j01/dialog/css/j01.dialog.css
src/j01/dialog/img/close.gif
src/j01/dialog/img/close.png
src/j01/dialog/img/dialog.png
src/j01/dialog/img/dialogBG.gif
src/j01/dialog/img/dialogBGContent.gif
src/j01/dialog/img/dialogBL.gif
src/j01/dialog/img/dialogBR.gif
src/j01/dialog/img/dialogBorder.gif
src/j01/dialog/img/dialogTL.gif
src/j01/dialog/img/dialogTR.gif
src/j01/dialog/js/j01.dialog.js
src/j01/dialog/test/dialog.html
src/j01/dialog/test/index.html
src/j01/dialog/test/jquery-1.2.js
src/j01/dialog/test/test.html
src/j01/dialog/test/test.js
src/j01/dialog/test/testrunner.js
src/j01/dialog/test/testsuite.css